{
  "tickers": {
    "VWCE": {
      "consecutive_failures": 0,
      "last_success": "2026-07-08T20:01:22.845253+00:00",
      "last_source": "yfinance",
      "alert_needed": false
    },
    "CSNDX": {
      "consecutive_failures": 0,
      "last_success": "2026-07-08T20:01:23.100686+00:00",
      "last_source": "yfinance",
      "alert_needed": false
    },
    "CSPX": {
      "consecutive_failures": 0,
      "last_success": "2026-07-08T20:01:23.353070+00:00",
      "last_source": "yfinance",
      "alert_needed": false
    },
    "SWDA": {
      "consecutive_failures": 0,
      "last_success": "2026-07-08T20:01:23.950127+00:00",
      "last_source": "yfinance",
      "alert_needed": false
    },
    "VETA": {
      "consecutive_failures": 0,
      "last_success": "2026-07-08T20:01:24.211240+00:00",
      "last_source": "yfinance",
      "alert_needed": false,
      "last_failure": "2026-07-07T20:25:17.607567+00:00"
    }
  },
  "updated_at": "2026-07-08T20:01:22.039023+00:00"
}
